oddl/__init__.py
oddl/app.py
oddl/gui.py
oddl/opendaprequest.py
oddl-0.1.2.dist-info/LICENSE
oddl-0.1.2.dist-info/METADATA
oddl-0.1.2.dist-info/WHEEL
oddl-0.1.2.dist-info/entry_points.txt
oddl-0.1.2.dist-info/top_level.txt
oddl-0.1.2.dist-info/RECORD
