Metadata-Version: 2.1
Name: oddl
Version: 0.1.2
Summary: oddl (OpeNDAP Downloader): a GUI-based Python app for downloading and saving netCDF data via OpeNDAP.
Home-page: https://github.com/ChrisDrozdowski/oddl
Author: Chris Drozdowski
Author-email: drozdowski.chris@gmail.com
License: MIT License
Keywords: netcdf,data science,climate,opendap
Platform: UNKNOWN
Classifier: Development Status :: 4 - Beta
Classifier: Intended Audience :: Science/Research
Classifier: License :: OSI Approved :: MIT License
Classifier: Natural Language :: English
Classifier: Operating System :: OS Independent
Classifier: Programming Language :: Python :: 3.8
Classifier: Programming Language :: Python :: 3.9
Classifier: Topic :: Scientific/Engineering :: Atmospheric Science
Requires-Python: >=3.8.0
Requires-Dist: netCDF4
Requires-Dist: xarray
Requires-Dist: dask[complete]
Requires-Dist: pydap
Requires-Dist: requests
Requires-Dist: lxml
